dom_heal/__init__.py
dom_heal/cli.py
dom_heal/comparator.py
dom_heal/engine.py
dom_heal/extractor.py
dom_heal/healing.py
dom_heal/utils.py
dom_heal-1.0.0.dist-info/licenses/LICENSE
dom_heal-1.0.0.dist-info/METADATA
dom_heal-1.0.0.dist-info/WHEEL
dom_heal-1.0.0.dist-info/entry_points.txt
dom_heal-1.0.0.dist-info/top_level.txt
dom_heal-1.0.0.dist-info/RECORD
