Metadata-Version: 2.4
Name: dom-heal
Version: 1.0.0
Summary: Auto-recuperação de seletores DOM para testes web
Home-page: https://github.com/jonnaschristian/dom-heal
Author: Jonnas Christian Sousa de Paiva
Author-email: jonnaschristian@gmail.com
Classifier: Programming Language :: Python :: 3
Classifier: Operating System :: OS Independent
Classifier: Intended Audience :: Developers
Classifier: Intended Audience :: Information Technology
Classifier: Topic :: Software Development :: Testing
Classifier: License :: OSI Approved :: MIT License
Requires-Python: >=3.7
License-File: LICENSE
Requires-Dist: rapidfuzz>=3.13.0
Requires-Dist: selenium>=4.29.0
Requires-Dist: webdriver-manager>=4.0.2
Requires-Dist: typer[all]>=0.9.0
Requires-Dist: lxml>=4.9.0
Requires-Dist: requests>=2.25.0
Provides-Extra: dev
Requires-Dist: pytest>=8.0.0; extra == "dev"
Requires-Dist: python-dotenv>=1.0.0; extra == "dev"
Dynamic: author
Dynamic: author-email
Dynamic: classifier
Dynamic: description
Dynamic: description-content-type
Dynamic: home-page
Dynamic: license-file
Dynamic: provides-extra
Dynamic: requires-dist
Dynamic: requires-python
Dynamic: summary
